{
    "Nome": [
        "ADMINISTRAÇÃO PÚBLICA EM REDE NACIONAL"
    ],
    "Coordenador(a)": [
        "TERESA CRISTINA JANES CARNEIRO"
    ],
    "Nome do Programa em Inglês": [
        "PUBLIC ADMINISTRATION IN NATIONAL NETWORK"
    ],
    "Código": [
        "53045009001P3"
    ],
    "Área Básica": [
        "ADMINISTRAÇÃO PÚBLICA (60202009)"
    ],
    "Área de Avaliação": [
        "ADMINISTRAÇÃO PÚBLICA E DE EMPRESAS, CIÊNCIAS CONTÁBEIS E TURISMO"
    ],
    "Situação": [
        "EM FUNCIONAMENTO"
    ],
    "Modalidade de Ensino": [
        "Educação Presencial"
    ],
    "Observações": []
}